{"translation":"oeb-us","book":"psa","bookName":"Psalms","chapter":16,"verses":[{"number":1,"text":"Keep me, O God, for in you I take refuge."},{"number":2,"text":"I said to the Lord, “You are my Lord, my happiness rests in you alone."},{"number":3,"text":"Those who are holy in the land, they, they alone, are the noble ones; all my delight is in them.”"},{"number":4,"text":"Those who choose other gods find endless sorrow. In their offerings of blood I will have no part nor take their name on my lips."},{"number":5,"text":"The Lord is my share and my portion, my fate is in your strong hands."},{"number":6,"text":"The boundary lines of my life mark out delightful country, my heritage pleases me well."},{"number":7,"text":"I praise the Lord for his counsel, which so stirs my heart in the night."},{"number":8,"text":"I keep the Lord always in mind: with him at my hand, I can never be moved."},{"number":9,"text":"So my heart is glad, there is joy inside me; and in safety of body I live."},{"number":10,"text":"For you will not give me up to Sheol nor let any who love you see the pit."},{"number":11,"text":"You will show me the path that leads to life, to that fulness of joy which is in your presence, and the pleasures dispensed by your hand evermore."}]}